gsttaxlib/__init__.py
gsttaxlib/gstcommonfunctions.py
gsttaxlib-0.1.0.dist-info/METADATA
gsttaxlib-0.1.0.dist-info/WHEEL
gsttaxlib-0.1.0.dist-info/top_level.txt
gsttaxlib-0.1.0.dist-info/RECORD
