Metadata-Version: 2.1
Name: gsttaxlib
Version: 0.1.0
Summary: GST Tax Library
Author: x21146331_Mahesh_Prakash_Ravi
License: NCI
Platform: UNKNOWN
